pybiographical/__init__.py
pybiographical/env.py
pybiographical/ramdisk.py
pybiographical/io/__init__.py
pybiographical/io/yaml_utils.py
pybiographical/locations/__init__.py
pybiographical/locations/models.py
pybiographical/locations/registry.py
pybiographical/matching/__init__.py
pybiographical/matching/fuzzy.py
pybiographical/names/__init__.py
pybiographical/names/models.py
pybiographical/names/registry.py
pybiographical/names/resolver.py
pybiographical/persons/__init__.py
pybiographical/persons/crud.py
pybiographical/persons/models.py
pybiographical/persons/validation.py
pybiographical-0.2.1.dist-info/METADATA
pybiographical-0.2.1.dist-info/WHEEL
pybiographical-0.2.1.dist-info/top_level.txt
pybiographical-0.2.1.dist-info/RECORD
