Metadata-Version: 2.4
Name: pybiographical
Version: 0.2.1
Summary: Python library for working with biographical data points for persons and locations
Author-email: Jane Smith <developer@example.com>
License: MIT
Project-URL: Homepage, https://github.com/rickhohler/PyBiographical
Project-URL: Repository, https://github.com/rickhohler/PyBiographical
Project-URL: Issues, https://github.com/rickhohler/PyBiographical/issues
Project-URL: Changelog, https://github.com/rickhohler/PyBiographical/blob/main/CHANGELOG.md
Keywords: biographical,metadata,person-data,location-data,fuzzy-matching,yaml,data-management
Classifier: Development Status :: 3 - Alpha
Classifier: Intended Audience :: Developers
Classifier: License :: OSI Approved :: MIT License
Classifier: Operating System :: OS Independent
Classifier: Programming Language :: Python :: 3
Classifier: Programming Language :: Python :: 3.8
Classifier: Programming Language :: Python :: 3.9
Classifier: Programming Language :: Python :: 3.10
Classifier: Programming Language :: Python :: 3.11
Classifier: Topic :: Software Development :: Libraries :: Python Modules
Classifier: Topic :: Scientific/Engineering :: Information Analysis
Requires-Python: >=3.8
Requires-Dist: ruamel.yaml>=0.17.0
Provides-Extra: dev
Requires-Dist: pytest>=7.0; extra == "dev"
Requires-Dist: pytest-cov>=4.0; extra == "dev"
Requires-Dist: black>=23.0; extra == "dev"
Requires-Dist: ruff>=0.1; extra == "dev"
Provides-Extra: matching
Requires-Dist: rapidfuzz>=3.0.0; extra == "matching"
Provides-Extra: full
Requires-Dist: ruamel.yaml>=0.17.0; extra == "full"
Requires-Dist: rapidfuzz>=3.0.0; extra == "full"
